StwControlsStadian.v
module StwControl(reset, clock, SW_F1, SW_F2, STW_ON, STW_RST_N, CLK, RST);
  input reset;
  input clock;
  input SW_F1;
  input SW_F2;
  output STW_ON;
  output STW_RST_N;
  input CLK;
  input RST;

  reg STW_ON;
  reg STW_RST_N;

  parameter [1:0] IDLE = 0, RUN = 1, HOLD = 2;
  reg [1:0] current_state, next_state;

  always @(posedge clock or posedge reset)
  begin: SYNCH
    if (reset == 1'b1)
       current_state <= IDLE;
    else
       current_state <= next_state;
  end

  always @(current_state or SW_F1 or SW_F2 or CLK or RST)
  begin: COMBIN
     case (current_state)
        IDLE:
        begin
          if (!(SW_F1))
             begin
             next_state <= IDLE;
             end
          else if (SW_F1)
             begin
             next_state <= RUN;
             end
          else
             begin
             next_state <= IDLE;
             end
          STW_ON <= 1'b0;

        end

        RUN:
        begin
          if (!(SW_F1) && !(SW_F2))
             begin
             next_state <= RUN;
             end
          else if (SW_F2)
             begin
             next_state <= IDLE;
             end
          else if (SW_F1 && !(SW_F2))
             begin
             next_state <= HOLD;
             end
          STW_ON <= 1'b1;

        end

        HOLD:
        begin
          if (!(SW_F1) && !(SW_F2))
             begin
             next_state <= HOLD;
             end
          else if (SW_F2)
             begin
             next_state <= IDLE;
             end
          else if (SW_F1 && !(SW_F2))
             begin
             next_state <= RUN;
             end
          STW_ON <= 1'b0;

        end


        default:
          next_state <= IDLE;
     endcase
  end

endmodule

StwControl_tb.v
module StwControl_tb;

reg SW_F1;
reg CLK;
reg RST;
reg SW_F2;
wire STW_ON;
wire STW_RST_N;

StwControl
 U0 (
  .SW_F1(SW_F1),
  .CLK(CLK),
  .RST(RST),
  .SW_F2(SW_F2),
  .STW_ON(STW_ON),
  .STW_RST_N(STW_RST_N));

  initial
  begin
    SW_F1 = 1'b0;
    #200 SW_F1 = 1'b1;
    #100 SW_F1 = 1'b0;
    #400 SW_F1 = 1'b1;
    #100 SW_F1 = 1'b0;
    #200 SW_F1 = 1'b1;
    #100 SW_F1 = 1'b0;
    #500 SW_F1 = 1'b1;
    #100 SW_F1 = 1'b0;
    #600 SW_F1 = 1'b1;
    #100 SW_F1 = 1'b0;
    #200 SW_F1 = 1'b1;
    #100 SW_F1 = 1'b0;
  end

  initial
    CLK = 1'b0;

  always
  begin : GenCLK
    #50 CLK = 1'b1;
    #50 CLK = 1'b0;
  end

  initial
  begin
    RST = 1'b0;
    #100 RST = 1'b1;
    #100 RST = 1'b0;
  end

  initial
  begin
    SW_F2 = 1'b0;
    #1300 SW_F2 = 1'b1;
    #100 SW_F2 = 1'b0;
    #600 SW_F2 = 1'b1;
    #100 SW_F2 = 1'b0;
    #800 SW_F2 = 1'b1;
    #100 SW_F2 = 1'b0;
  end

endmodule

_service/20171223173318_SimulateISim_ace913_StwControl_tb/StwControl_tb.vcd
$date
   Sat Dec 23 17:33:23 2017
$end
$version
  P.15xf
$end
$timescale
  1ps
$end
$scope module StwControl_tb $end
$var wire 1 ! STW_ON $end
$var wire 1 " STW_RST_N $end
$var reg 1 # SW_F1 $end
$var reg 1 $ CLK $end
$var reg 1 % RST $end
$var reg 1 & SW_F2 $end
$upscope $end
$enddefinitions $end
#0
$dumpvars
0#
0$
0%
0&
x!
x"
$end
#50000
1$
#100000
0$
1%
0!
0"
#150000
1$
#200000
1#
0$
0%
#250000
1$
1!
1"
#300000
0#
0$
#350000
1$
#400000
0$
#450000
1$
#500000
0$
#550000
1$
#600000
0$
#650000
1$
#700000
1#
0$
#750000
1$
0!
#800000
0#
0$
#850000
1$
#900000
0$
#950000
1$
#1000000
1#
0$
#1050000
1$
1!
#1100000
0#
0$
#1150000
1$
#1200000
0$
#1250000
1$
#1300000
0$
1&
#1350000
1$
0!
0"
#1400000
0$
0&
#1450000
1$
#1500000
0$
#1550000
1$
#1600000
1#
0$
#1650000
1$
1!
1"
#1700000
0#
0$
#1750000
1$
#1800000
0$
#1850000
1$
#1900000
0$
#1950000
1$
#2000000
0$
1&
#2050000
1$
0!
0"
#2100000
0$
0&
#2150000
1$
#2200000
0$
#2250000
1$
#2300000
1#
0$
#2350000
1$
1!
1"
#2400000
0#
0$
#2450000
1$
#2500000
0$
#2550000
1$
#2600000
1#
0$
#2650000
1$
0!
#2700000
0#
0$
#2750000
1$
#2800000
0$
#2850000
1$
#2900000
0$
1&
#2950000
1$
0"
#3000000
0$
0&
